dorsa_logging/__init__.py
dorsa_logging/logging_funcs.py
dorsa_logging-1.1.0.dist-info/LICENSE.txt
dorsa_logging-1.1.0.dist-info/METADATA
dorsa_logging-1.1.0.dist-info/WHEEL
dorsa_logging-1.1.0.dist-info/top_level.txt
dorsa_logging-1.1.0.dist-info/RECORD
