Metadata-Version: 2.1
Name: dorsa-logging
Version: 1.1.0
Summary: Log application happenings
Home-page: https://github.com/DORSA-co/modules/tree/main/Dorsa_Logging
Author: Dorsa-co
Author-email: info@dorsa-co.ir
License: Apache License 2.0
Project-URL: Bug Tracker, https://github.com/DORSA-co/modules/tree/main/Dorsa_Logging/issues
Keywords: pypi,dorsa_logging
Classifier: Intended Audience :: Developers
Classifier: Topic :: Software Development :: Documentation
Classifier: License :: OSI Approved :: Apache Software License
Classifier: Programming Language :: Python :: 3
Classifier: Programming Language :: Python :: 3.7
Classifier: Programming Language :: Python :: 3.8
Classifier: Programming Language :: Python :: 3.9
Classifier: Programming Language :: Python :: 3.10
License-File: LICENSE.txt
Requires-Dist: dorsa-datetime
